<?xml version="1.0" encoding="UTF-8"?>
<descriptions>
   <description count="1" length="6" conceptId="normal" type="pref" language="en-US"
                superClasses=""
                classificationId="2.16.840.1.113883.5.14"
                classificationName="ActStatus">normal</description>
   <description count="1" length="9" conceptId="nullified" type="pref" language="en-US"
                superClasses=""
                classificationId="2.16.840.1.113883.5.14"
                classificationName="ActStatus">nullified</description>
   <description count="1" length="8" conceptId="obsolete" type="pref" language="en-US"
                superClasses=""
                classificationId="2.16.840.1.113883.5.14"
                classificationName="ActStatus">obsolete</description>
   <description count="1" length="7" conceptId="aborted" type="pref" language="en-US"
                superClasses="normal"
                classificationId="2.16.840.1.113883.5.14"
                classificationName="ActStatus">aborted</description>
   <description count="1" length="6" conceptId="active" type="pref" language="en-US"
                superClasses="normal"
                classificationId="2.16.840.1.113883.5.14"
                classificationName="ActStatus">active</description>
   <description count="1" length="9" conceptId="cancelled" type="pref" language="en-US"
                superClasses="normal"
                classificationId="2.16.840.1.113883.5.14"
                classificationName="ActStatus">cancelled</description>
   <description count="1" length="9" conceptId="completed" type="pref" language="en-US"
                superClasses="normal"
                classificationId="2.16.840.1.113883.5.14"
                classificationName="ActStatus">completed</description>
   <description count="1" length="4" conceptId="held" type="pref" language="en-US"
                superClasses="normal"
                classificationId="2.16.840.1.113883.5.14"
                classificationName="ActStatus">held</description>
   <description count="1" length="3" conceptId="new" type="pref" language="en-US"
                superClasses="normal"
                classificationId="2.16.840.1.113883.5.14"
                classificationName="ActStatus">new</description>
   <description count="1" length="9" conceptId="suspended" type="pref" language="en-US"
                superClasses="normal"
                classificationId="2.16.840.1.113883.5.14"
                classificationName="ActStatus">suspended</description>
</descriptions>