<?xml version="1.0" encoding="UTF-8"?>
<descriptions>
   <description count="1" length="22" conceptId="_CalendarCycleOneLetter" type="pref"
                language="en-US"
                superClasses=""
                classificationId="2.16.840.1.113883.5.9"
                classificationName="CalendarCycle">CalendarCycleOneLetter</description>
   <description count="1" length="22" conceptId="_CalendarCycleTwoLetter" type="pref"
                language="en-US"
                superClasses=""
                classificationId="2.16.840.1.113883.5.9"
                classificationName="CalendarCycle">CalendarCycleTwoLetter</description>
   <description count="2" length="17" conceptId="CW W" type="pref" language="en-US"
                superClasses="CalendarCycleOneLetter, CalendarCycleTwoLetter"
                classificationId="2.16.840.1.113883.5.9"
                classificationName="CalendarCycle">week (continuous)</description>
   <description count="1" length="4" conceptId="CY Y" type="pref" language="en-US"
                superClasses="CalendarCycleOneLetter, CalendarCycleTwoLetter"
                classificationId="2.16.840.1.113883.5.9"
                classificationName="CalendarCycle">year</description>
   <description count="4" length="16" conceptId="D DM" type="pref" language="en-US"
                superClasses="CalendarCycleOneLetter, CalendarCycleTwoLetter"
                classificationId="2.16.840.1.113883.5.9"
                classificationName="CalendarCycle">day of the month</description>
   <description count="7" length="36" conceptId="DW J" type="pref" language="en-US"
                superClasses="CalendarCycleOneLetter, CalendarCycleTwoLetter"
                classificationId="2.16.840.1.113883.5.9"
                classificationName="CalendarCycle">day of the week (begins with Monday)</description>
   <description count="4" length="15" conceptId="H HD" type="pref" language="en-US"
                superClasses="CalendarCycleOneLetter, CalendarCycleTwoLetter"
                classificationId="2.16.840.1.113883.5.9"
                classificationName="CalendarCycle">hour of the day</description>
   <description count="4" length="17" conceptId="M MY" type="pref" language="en-US"
                superClasses="CalendarCycleOneLetter, CalendarCycleTwoLetter"
                classificationId="2.16.840.1.113883.5.9"
                classificationName="CalendarCycle">month of the year</description>
   <description count="4" length="18" conceptId="N NH" type="pref" language="en-US"
                superClasses="CalendarCycleOneLetter, CalendarCycleTwoLetter"
                classificationId="2.16.840.1.113883.5.9"
                classificationName="CalendarCycle">minute of the hour</description>
   <description count="4" length="20" conceptId="S SN" type="pref" language="en-US"
                superClasses="CalendarCycleOneLetter, CalendarCycleTwoLetter"
                classificationId="2.16.840.1.113883.5.9"
                classificationName="CalendarCycle">second of the minute</description>
   <description count="1" length="22" conceptId="_GregorianCalendarCycle" type="pref"
                language="en-US"
                superClasses="CalendarCycleTwoLetter"
                classificationId="2.16.840.1.113883.5.9"
                classificationName="CalendarCycle">GregorianCalendarCycle</description>
   <description count="2" length="16" conceptId="CD" type="pref" language="en-US"
                superClasses="CalendarCycleTwoLetter"
                classificationId="2.16.840.1.113883.5.9"
                classificationName="CalendarCycle">day (continuous)</description>
   <description count="2" length="17" conceptId="CH" type="pref" language="en-US"
                superClasses="CalendarCycleTwoLetter"
                classificationId="2.16.840.1.113883.5.9"
                classificationName="CalendarCycle">hour (continuous)</description>
   <description count="2" length="18" conceptId="CM" type="pref" language="en-US"
                superClasses="CalendarCycleTwoLetter"
                classificationId="2.16.840.1.113883.5.9"
                classificationName="CalendarCycle">month (continuous)</description>
   <description count="2" length="19" conceptId="CN" type="pref" language="en-US"
                superClasses="CalendarCycleTwoLetter"
                classificationId="2.16.840.1.113883.5.9"
                classificationName="CalendarCycle">minute (continuous)</description>
   <description count="2" length="19" conceptId="CS" type="pref" language="en-US"
                superClasses="CalendarCycleTwoLetter"
                classificationId="2.16.840.1.113883.5.9"
                classificationName="CalendarCycle">second (continuous)</description>
   <description count="4" length="15" conceptId="DY" type="pref" language="en-US"
                superClasses="CalendarCycleTwoLetter"
                classificationId="2.16.840.1.113883.5.9"
                classificationName="CalendarCycle">day of the year</description>
   <description count="4" length="16" conceptId="WY" type="pref" language="en-US"
                superClasses="CalendarCycleTwoLetter"
                classificationId="2.16.840.1.113883.5.9"
                classificationName="CalendarCycle">week of the year</description>
</descriptions>